xframe/.xframe-complete.bash
xframe/.xframe-complete.fish
xframe/.xframe-complete.zsh
xframe/Multiprocessing.py
xframe/Multiprocessing_interfaces.py
xframe/__init__.py
xframe/_version.py
xframe/interfaces.py
xframe/logger.py
xframe/main.py
xframe/startup_routines.py
xframe/control/Control.py
xframe/control/__init__.py
xframe/control/communicators.py
xframe/control/interfaces.py
xframe/database/__init__.py
xframe/database/database.py
xframe/database/interfaces.py
xframe/experiments/__init__.py
xframe/experiments/SPB/__init__.py
xframe/experiments/SPB/_database_.py
xframe/experiments/SPB/default.geom
xframe/experiments/SPB/experiment.py
xframe/experiments/SPB/interfaces.py
xframe/experiments/SPB/calibrators/__init__.py
xframe/experiments/SPB/calibrators/calibrators.py
xframe/experiments/SPB/detectors/__init__.py
xframe/experiments/SPB/detectors/agipd.py
xframe/experiments/SPB/detectors/interfaces.py
xframe/experiments/SPB/expLibrary/__init__.py
xframe/experiments/SPB/expLibrary/centering.py
xframe/experiments/SPB/expLibrary/classes.py
xframe/experiments/SPB/expLibrary/cross_correlation.py
xframe/experiments/SPB/expLibrary/figures.py
xframe/experiments/SPB/expLibrary/filters.py
xframe/experiments/SPB/expLibrary/misk.py
xframe/experiments/SPB/expLibrary/quantities.py
xframe/experiments/SPB/expLibrary/regrid.py
xframe/experiments/SPB/expLibrary/regrid2.py
xframe/experiments/SPB/expLibrary/rois.py
xframe/experiments/SPB/expLibrary/saxs.py
xframe/experiments/SPB/settings/default_0.01.yaml
xframe/experiments/SPB/settings/tutorial.yaml
xframe/experiments/SPB/simulators/EasySimulators.py
xframe/experiments/SPB/simulators/interfaces.py
xframe/externalLibraries/__init__.py
xframe/externalLibraries/arb_plugin.py
xframe/externalLibraries/click_plugin.py
xframe/externalLibraries/cv_plugin.py
xframe/externalLibraries/flt_plugin.py
xframe/externalLibraries/gsl_plugin.py
xframe/externalLibraries/hdf5_plugin.py
xframe/externalLibraries/matplotlib_plugin.py
xframe-0.9.8.dist-info/LICENSE
xframe-0.9.8.dist-info/METADATA
xframe-0.9.8.dist-info/WHEEL
xframe-0.9.8.dist-info/entry_points.txt
xframe-0.9.8.dist-info/top_level.txt
xframe-0.9.8.dist-info/RECORD
