Metadata-Version: 2.1
Name: xframe
Version: 0.9.8
Summary: A framework for scientific algorithms targeting X-ray scattering
Author-email: Tim Berberich <tim.berberich@xfel.eu>
Project-URL: Homepage, https://github.com/European-XFEL/xFrame
Project-URL: Documentation, https://xframe-fxs.readthedocs.io
Keywords: scientific computing,xray,FXS,physics
Classifier: Intended Audience :: Science/Research
Classifier: Intended Audience :: Developers
Classifier: License :: OSI Approved :: Mozilla Public License 2.0 (MPL 2.0)
Classifier: Programming Language :: Python :: 3
Requires-Python: >=3.8
License-File: LICENSE
Requires-Dist: h5py
Requires-Dist: numpy
Requires-Dist: ruamel.yaml
Requires-Dist: scipy
Requires-Dist: click
Requires-Dist: psutil
Provides-Extra: all
Requires-Dist: pysofft ; extra == 'all'
Requires-Dist: shtns ; extra == 'all'
Requires-Dist: pyopencl ; extra == 'all'
Requires-Dist: vtk ; extra == 'all'
Requires-Dist: matplotlib ; extra == 'all'
Requires-Dist: opencv-python ; extra == 'all'
Requires-Dist: pygsl ; extra == 'all'
Requires-Dist: psutil ; extra == 'all'
Requires-Dist: flt ; extra == 'all'
Requires-Dist: SharedArray ; extra == 'all'
Provides-Extra: fxs
Requires-Dist: pysofft ; extra == 'fxs'
Requires-Dist: shtns ; extra == 'fxs'
Requires-Dist: pyopencl ; extra == 'fxs'
Requires-Dist: vtk ; extra == 'fxs'
Requires-Dist: matplotlib ; extra == 'fxs'
Requires-Dist: opencv-python ; extra == 'fxs'
Requires-Dist: pygsl ; extra == 'fxs'
Requires-Dist: psutil ; extra == 'fxs'
Requires-Dist: flt ; extra == 'fxs'
